pdf_combiner/__init__.py
pdf_combiner/__main__.py
pdf_combiner/image_to_pdf.py
pdf_combiner/input.py
pdf_combiner/pdf_combiner.py
pdf_combiner/util.py
scripts/format.py
scripts/generate_installer.py
scripts/test_python_source.py
tests/test_image_to_pdf.py
tests/test_inputs.py
pdf_combiner-0.0.3.dist-info/LICENSE.md
pdf_combiner-0.0.3.dist-info/METADATA
pdf_combiner-0.0.3.dist-info/WHEEL
pdf_combiner-0.0.3.dist-info/entry_points.txt
pdf_combiner-0.0.3.dist-info/top_level.txt
pdf_combiner-0.0.3.dist-info/RECORD
