Metadata-Version: 2.1
Name: pdf_combiner
Version: 0.0.3
Summary: PDF Combining Utility
Author: Sahil Kale
License: Prosperity 3.0.0
Project-URL: Homepage, https://github.com/sahil-kale/pdf-combiner
Project-URL: Issues, https://github.com/sahil-kale/pdf-combiner/issues
Requires-Python: >=3.7
License-File: LICENSE.md
Requires-Dist: pikepdf
Requires-Dist: pillow
Requires-Dist: click
